sqlitestructure/__init__.py
sqlitestructure/_interface.py
sqlitestructure/_writer.py
sqlitestructure-0.2.0.dist-info/DESCRIPTION.rst
sqlitestructure-0.2.0.dist-info/METADATA
sqlitestructure-0.2.0.dist-info/RECORD
sqlitestructure-0.2.0.dist-info/WHEEL
sqlitestructure-0.2.0.dist-info/metadata.json
sqlitestructure-0.2.0.dist-info/top_level.txt
