Metadata-Version: 2.0
Name: sqlitestructure
Version: 0.2.0
Summary:     sqlitestructure is a Python library to dump table structure of
Home-page: https://github.com/thombashi/sqlitestructure
Author: Tsuyoshi Hombashi
Author-email: gogogo.vm@gmail.com
License: MIT License
Keywords: SQLite,library
Platform: UNKNOWN
Classifier: Development Status :: 4 - Beta
Classifier: Intended Audience :: Developers
Classifier: License :: OSI Approved :: MIT License
Classifier: Operating System :: POSIX
Classifier: Operating System :: POSIX :: Linux
Classifier: Programming Language :: Python :: 2
Classifier: Programming Language :: Python :: 2.7
Classifier: Programming Language :: Python :: 3
Classifier: Programming Language :: Python :: 3.3
Classifier: Programming Language :: Python :: 3.4
Classifier: Programming Language :: Python :: 3.5
Classifier: Topic :: Software Development :: Libraries
Classifier: Topic :: Software Development :: Libraries :: Python Modules
Requires-Dist: DataProperty (>=0.13.0)
Requires-Dist: SimpleSQLite (>=0.6.6)
Requires-Dist: click
Requires-Dist: six
